experiments/demo/demo.sv
module demo (
  input clk,
  output reg [5:0] counter
);
  initial counter = 0;

  always @(posedge clk) begin
    if (counter == 33)
      counter <= 0;
    else
      counter <= counter + 1;
  end

`ifdef FORMAL
  always @(posedge clk) begin
    assert (counter < 32);
  end
`endif
endmodule

experiments/demo/demo/engine_0/trace.vcd
$version Generated by Yosys-SMTBMC $end
$timescale 1ns $end
$var integer 32 t smt_step $end
$var event 1 ! smt_clock $end
$scope module demo $end
$var wire 1 n0 clk $end
$var wire 6 n1 counter $end
$upscope $end
$enddefinitions $end
#0
1!
b00000000000000000000000000000000 t
b1 n0
b000000 n1
#5
b0 n0
#10
1!
b00000000000000000000000000000001 t
b1 n0
b000001 n1
#15
b0 n0
#20
1!
b00000000000000000000000000000010 t
b1 n0
b000010 n1
#25
b0 n0
#30
1!
b00000000000000000000000000000011 t
b1 n0
b000011 n1
#35
b0 n0
#40
1!
b00000000000000000000000000000100 t
b1 n0
b000100 n1
#45
b0 n0
#50
1!
b00000000000000000000000000000101 t
b1 n0
b000101 n1
#55
b0 n0
#60
1!
b00000000000000000000000000000110 t
b1 n0
b000110 n1
#65
b0 n0
#70
1!
b00000000000000000000000000000111 t
b1 n0
b000111 n1
#75
b0 n0
#80
1!
b00000000000000000000000000001000 t
b1 n0
b001000 n1
#85
b0 n0
#90
1!
b00000000000000000000000000001001 t
b1 n0
b001001 n1
#95
b0 n0
#100
1!
b00000000000000000000000000001010 t
b1 n0
b001010 n1
#105
b0 n0
#110
1!
b00000000000000000000000000001011 t
b1 n0
b001011 n1
#115
b0 n0
#120
1!
b00000000000000000000000000001100 t
b1 n0
b001100 n1
#125
b0 n0
#130
1!
b00000000000000000000000000001101 t
b1 n0
b001101 n1
#135
b0 n0
#140
1!
b00000000000000000000000000001110 t
b1 n0
b001110 n1
#145
b0 n0
#150
1!
b00000000000000000000000000001111 t
b1 n0
b001111 n1
#155
b0 n0
#160
1!
b00000000000000000000000000010000 t
b1 n0
b010000 n1
#165
b0 n0
#170
1!
b00000000000000000000000000010001 t
b1 n0
b010001 n1
#175
b0 n0
#180
1!
b00000000000000000000000000010010 t
b1 n0
b010010 n1
#185
b0 n0
#190
1!
b00000000000000000000000000010011 t
b1 n0
b010011 n1
#195
b0 n0
#200
1!
b00000000000000000000000000010100 t
b1 n0
b010100 n1
#205
b0 n0
#210
1!
b00000000000000000000000000010101 t
b1 n0
b010101 n1
#215
b0 n0
#220
1!
b00000000000000000000000000010110 t
b1 n0
b010110 n1
#225
b0 n0
#230
1!
b00000000000000000000000000010111 t
b1 n0
b010111 n1
#235
b0 n0
#240
1!
b00000000000000000000000000011000 t
b1 n0
b011000 n1
#245
b0 n0
#250
1!
b00000000000000000000000000011001 t
b1 n0
b011001 n1
#255
b0 n0
#260
1!
b00000000000000000000000000011010 t
b1 n0
b011010 n1
#265
b0 n0
#270
1!
b00000000000000000000000000011011 t
b1 n0
b011011 n1
#275
b0 n0
#280
1!
b00000000000000000000000000011100 t
b1 n0
b011100 n1
#285
b0 n0
#290
1!
b00000000000000000000000000011101 t
b1 n0
b011101 n1
#295
b0 n0
#300
1!
b00000000000000000000000000011110 t
b1 n0
b011110 n1
#305
b0 n0
#310
1!
b00000000000000000000000000011111 t
b1 n0
b011111 n1
#315
b0 n0
#320
1!
b00000000000000000000000000100000 t
b1 n0
b100000 n1
#325
b0 n0
#330
1!
b00000000000000000000000000100001 t
b1 n0
b100001 n1
#335
b0 n0
#340
1!
b00000000000000000000000000100010 t
b1 n0
