formal-intro-course/exercises/part4/fv-busy-counter/busyctr_prove/src/busyctr.v
// Copyright (C) 2017-2018, Gisselquist Technology, LLC
// See LICENSE for more details.
`default_nettype	none
module	busyctr(i_clk, i_reset, i_start_signal, o_busy);
	parameter	[15:0]	MAX_AMOUNT = 1000;
	input	wire	i_clk, i_reset;
	input	wire	i_start_signal;
	output	reg	o_busy;

	reg	[15:0]	counter;
    (* anyseq *) wire [7:0] increment;

	initial	counter = 0;
	always @(posedge i_clk)
		if (i_reset)
			counter <= 0;
		else if ((i_start_signal)&&(counter == 0))
			counter <= MAX_AMOUNT-1'b1;
		else if (counter != 0)
			counter <= counter - increment;

	always @(*)
		o_busy <= (counter != 0);

`ifdef	FORMAL

    reg f_past_valid = 0;
    always @(posedge i_clk) 
        f_past_valid <= 1;

    //	1. Assume that once raised, i_start_signal will remain high until it
    //		is both high and the counter is no longer busy.
    //		Following (i_start_signal)&&(!o_busy), i_start_signal is no
    //		longer constrained--until it is raised again.
    always @(posedge i_clk) begin
        if(f_past_valid && $past(i_start_signal) && o_busy)
            assume(i_start_signal);
    end

    // #1, To Prove:
    //	2. o_busy will *always* be true any time the counter is non-zero.
    //	3. If the counter is non-zero, it should always be counting down
    always @(posedge i_clk) begin
        assume(!i_reset);
        if(counter)
            assert(o_busy);
        if(counter && f_past_valid && counter != MAX_AMOUNT - 1)
            // assert(counter == $past(counter) - $past(increment)); // Another way to do it without assume on increment
            assert(counter < $past(counter));
    end

    always @(posedge i_clk) begin
      if(f_past_valid) 
        cover(!o_busy && $past(o_busy));
        assume(increment>0);
        if(o_busy)
          assume(increment<=counter); // Less than or equal to, to prevent counter from being stuck at 0
      end

`endif
endmodule

formal-intro-course/exercises/part4/fv-busy-counter/busyctr_cover/engine_0/trace0.vcd
$version Generated by Yosys-SMTBMC $end
$timescale 1ns $end
$var integer 32 t smt_step $end
$var event 1 ! smt_clock $end
$scope module busyctr $end
$var wire 16 n0 counter $end
$var wire 1 n1 f_past_valid $end
$var wire 1 n2 i_clk $end
$var wire 1 n3 i_reset $end
$var wire 1 n4 i_start_signal $end
$var wire 8 n5 increment $end
$var wire 1 n6 o_busy $end
$upscope $end
$enddefinitions $end
#0
1!
b00000000000000000000000000000000 t
b1 n2
b0000000000000000 n0
b0 n1
b0 n3
b1 n4
b10000000 n5
b0 n6
#5
b0 n2
#10
1!
b00000000000000000000000000000001 t
b1 n2
b0000001111100111 n0
b1 n1
b0 n3
b1 n4
b11111000 n5
b1 n6
#15
b0 n2
#20
1!
b00000000000000000000000000000010 t
b1 n2
b0000001011101111 n0
b1 n1
b0 n3
b1 n4
b11111111 n5
b1 n6
#25
b0 n2
#30
1!
b00000000000000000000000000000011 t
b1 n2
b0000000111110000 n0
b1 n1
b0 n3
b1 n4
b11110001 n5
b1 n6
#35
b0 n2
#40
1!
b00000000000000000000000000000100 t
b1 n2
b0000000011111111 n0
b1 n1
b0 n3
b1 n4
b11111111 n5
b1 n6
#45
b0 n2
#50
1!
b00000000000000000000000000000101 t
b1 n2
b0000000000000000 n0
b1 n1
b0 n3
b0 n4
b10000000 n5
b0 n6
#55
b0 n2
#60
1!
b00000000000000000000000000000110 t
b1 n2
b0000000000000000 n0
b1 n1
b0 n3
b0 n4
b10000000 n5
b0 n6
#65
b0 n2
#70
1!
b00000000000000000000000000000111 t
b1 n2
