formal-intro-course/exercises/part1/wolf_goat_cabbage/wolf_goat_cabbage.sv
// A man needs to cross a river with a wolf, a goat and a cabbage. His boat is only large
// enough to carry himself and one of his three possessions, so he must transport these
// items one at a time. However, if he leaves the wolf and the goat together unattended,
// then the wolf will eat the goat; similarly, if he leaves the goat and the cabbage together
// unattended, then the goat will eat the cabbage. How can the man get across safely with
// his three items?

module wolf_goat_cabbage (input clk, input w, g, c);
	// everyone starts at the 1st river bank
	reg bank_w = 0; // wolf
	reg bank_g = 0; // goat
	reg bank_c = 0; // cabbage
	reg bank_m = 0; // man

	always @(posedge clk) begin
		// maximum one of the control signals must be high
		assume (w+g+c <= 1);

		// we want wolf, goat, and cabbage on the 2nd river bank
        // write a cover statement that will result in the desired combination
        cover(bank_w && bank_g && bank_c);

		// don't leave wolf and goat unattended
		if (bank_w != bank_m) begin
			assume (bank_w != bank_g);
		end

		// don't leave goat and cabbage unattended
		if (bank_g != bank_m) begin
			assume (bank_g != bank_c);
		end

		// man travels and takes the selected item with him
		if (w && (bank_w == bank_m)) bank_w <= !bank_m;
		if (g && (bank_g == bank_m)) bank_g <= !bank_m;
		if (c && (bank_c == bank_m)) bank_c <= !bank_m;
		bank_m <= !bank_m;
	end
endmodule

formal-intro-course/exercises/part1/wolf_goat_cabbage/wolf_goat_cabbage/engine_0/trace0.vcd
$version Generated by Yosys-SMTBMC $end
$timescale 1ns $end
$var integer 32 t smt_step $end
$var event 1 ! smt_clock $end
$scope module wolf_goat_cabbage $end
$var wire 1 n0 bank_c $end
$var wire 1 n1 bank_g $end
$var wire 1 n2 bank_m $end
$var wire 1 n3 bank_w $end
$var wire 1 n4 c $end
$var wire 1 n5 clk $end
$var wire 1 n6 g $end
$var wire 1 n7 w $end
$upscope $end
$enddefinitions $end
#0
1!
b00000000000000000000000000000000 t
b1 n5
b0 n0
b0 n1
b0 n2
b0 n3
b0 n4
b1 n6
b0 n7
#5
b0 n5
#10
1!
b00000000000000000000000000000001 t
b1 n5
b0 n0
b1 n1
b1 n2
b0 n3
b0 n4
b0 n6
b0 n7
#15
b0 n5
#20
1!
b00000000000000000000000000000010 t
b1 n5
b0 n0
b1 n1
b0 n2
b0 n3
b1 n4
b0 n6
b0 n7
#25
b0 n5
#30
1!
b00000000000000000000000000000011 t
b1 n5
b1 n0
b1 n1
b1 n2
b0 n3
b0 n4
b1 n6
b0 n7
#35
b0 n5
#40
1!
b00000000000000000000000000000100 t
b1 n5
b1 n0
b0 n1
b0 n2
b0 n3
b0 n4
b0 n6
b1 n7
#45
b0 n5
#50
1!
b00000000000000000000000000000101 t
b1 n5
b1 n0
b0 n1
b1 n2
b1 n3
b0 n4
b1 n6
b0 n7
#55
b0 n5
#60
1!
b00000000000000000000000000000110 t
b1 n5
b1 n0
b0 n1
b0 n2
b1 n3
b0 n4
b1 n6
b0 n7
#65
b0 n5
#70
1!
b00000000000000000000000000000111 t
b1 n5
b1 n0
b1 n1
b1 n2
b1 n3
b0 n4
b1 n6
b0 n7
#75
b0 n5
#80
1!
b00000000000000000000000000001000 t
b1 n5
b1 n0
b0 n1
b0 n2
b1 n3
b0 n4
b0 n6
b0 n7
#85
b0 n5
#90
1!
b00000000000000000000000000001001 t
b1 n5
